cf2cdm/__init__.py
cf2cdm/cfcoords.py
cf2cdm/cfunits.py
cf2cdm/datamodels.py
cfgrib/__init__.py
cfgrib/__main__.py
cfgrib/abc.py
cfgrib/cfmessage.py
cfgrib/dataset.py
cfgrib/messages.py
cfgrib/xarray_plugin.py
cfgrib/xarray_store.py
cfgrib/xarray_to_grib.py
cfgrib-0.9.15.0.dist-info/LICENSE
cfgrib-0.9.15.0.dist-info/METADATA
cfgrib-0.9.15.0.dist-info/WHEEL
cfgrib-0.9.15.0.dist-info/entry_points.txt
cfgrib-0.9.15.0.dist-info/top_level.txt
cfgrib-0.9.15.0.dist-info/zip-safe
cfgrib-0.9.15.0.dist-info/RECORD
