Metadata-Version: 2.1
Name: cfgrib
Version: 0.9.15.0
Summary: Python interface to map GRIB files to the NetCDF Common Data Model following the CF Convention using ecCodes.
Home-page: https://github.com/ecmwf/cfgrib
Author: European Centre for Medium-Range Weather Forecasts (ECMWF)
Author-email: software.support@ecmwf.int
License: Apache License Version 2.0
Keywords: eccodes grib xarray
Platform: UNKNOWN
Classifier: Development Status :: 4 - Beta
Classifier: Intended Audience :: Developers
Classifier: License :: OSI Approved :: Apache Software License
Classifier: Programming Language :: Python :: 3
Classifier: Programming Language :: Python :: 3.7
Classifier: Programming Language :: Python :: 3.8
Classifier: Programming Language :: Python :: 3.9
Classifier: Programming Language :: Python :: Implementation :: CPython
Classifier: Programming Language :: Python :: Implementation :: PyPy
Classifier: Operating System :: OS Independent
Requires-Python: >=3.7
Provides-Extra: xarray
Provides-Extra: tests
